wxmpy/__init__.py
wxmpy/wxm.py
wxmpy-1.0.2.dist-info/LICENSE
wxmpy-1.0.2.dist-info/METADATA
wxmpy-1.0.2.dist-info/WHEEL
wxmpy-1.0.2.dist-info/top_level.txt
wxmpy-1.0.2.dist-info/RECORD
